LICENSE
README.md
setup.cfg
setup.py
stdb/__init__.py
stdb/classes.py
stdb/convert.legacy.py
stdb/gui.py
stdb/io.py
stdb/kml.py
stdb.egg-info/PKG-INFO
stdb.egg-info/SOURCES.txt
stdb.egg-info/dependency_links.txt
stdb.egg-info/entry_points.txt
stdb.egg-info/requires.txt
stdb.egg-info/top_level.txt
stdb/examples/figures/P33M.png
stdb/examples/figures/P33M_gui.png
stdb/examples/figures/StDb_logo.ai
stdb/examples/figures/StDb_logo.png
stdb/examples/figures/StDb_logo_stripped.ai
stdb/examples/figures/StDb_logo_stripped.png
stdb/examples/figures/merged.png
stdb/scripts/__init__.py
stdb/scripts/append_stdb.py
stdb/scripts/dump_stdb.py
stdb/scripts/edit_stdb.py
stdb/scripts/gen_stdb.py
stdb/scripts/ls_stdb.py
stdb/scripts/merge_stdb.py
stdb/scripts/query_fdsn_stdb.py
stdb/scripts/stdb_to_kml.py