Metadata-Version: 2.2
Name: stdb
Version: 0.2.4
Summary: Python Module for managing Station Databases
Home-page: https://github.com/schaefferaj/StDb
Download-URL: https://github.com/schaefferaj/StDb/releases/tag/v0.2.4
Author: Andrew Schaeffer, Pascal Audet
Author-email: andrew.schaeffer@canada.ca, pascal.audet@uottawa.ca
Maintainer: Andrew Schaeffer, Pascal Audet
Maintainer-email: andrew.schaeffer@canada.ca, pascal.audet@uottawa.ca
Classifier: Development Status :: 3 - Alpha
Classifier: License :: OSI Approved :: MIT License
Classifier: Programming Language :: Python :: 3.6
Classifier: Programming Language :: Python :: 3.7
Classifier: Programming Language :: Python :: 3.8
Classifier: Programming Language :: Python :: 3.9
Requires-Python: >=3.6
License-File: LICENSE
Requires-Dist: obspy
Requires-Dist: PyQt5
Dynamic: author
Dynamic: author-email
Dynamic: classifier
Dynamic: download-url
Dynamic: home-page
Dynamic: maintainer
Dynamic: maintainer-email
Dynamic: requires-dist
Dynamic: requires-python
Dynamic: summary
